pybulletproofs-0.1.0_dev7.dist-info/METADATA
pybulletproofs-0.1.0_dev7.dist-info/WHEEL
pybulletproofs-0.1.0_dev7.dist-info/license_files/LICENSE
pybulletproofs/__init__.py
pybulletproofs/pybulletproofs.cpython-310-x86_64-linux-gnu.so
pybulletproofs-0.1.0_dev7.dist-info/RECORD
