Metadata-Version: 2.1
Name: pybulletproofs
Version: 0.1.0_dev7
Classifier: Development Status :: 2 - Pre-Alpha
Classifier: Programming Language :: Rust
Classifier: Programming Language :: Python :: Implementation :: CPython
Classifier: Programming Language :: Python :: Implementation :: PyPy
License-File: LICENSE
Summary: Python bindings to bulletproofs
Author: Lun Wang
Requires-Python: >=3.8
Project-URL: repository, https://github.com/initc3/pybulletproofs
